djcorecap/__init__.py
djcorecap/admin.py
djcorecap/apps.py
djcorecap/cli.py
djcorecap/core.py
djcorecap/forms.py
djcorecap/models.py
djcorecap/urls.py
djcorecap/utils.py
djcorecap/views.py
djcorecap/migrations/__init__.py
djcorecap/static/sass/project.scss
djcorecap/templates/base.html
djcorecap/templates/account/account_inactive.html
djcorecap/templates/account/base.html
djcorecap/templates/account/email.html
djcorecap/templates/account/email_confirm.html
djcorecap/templates/account/login.html
djcorecap/templates/account/logout.html
djcorecap/templates/account/password_change.html
djcorecap/templates/account/password_reset.html
djcorecap/templates/account/password_reset_done.html
djcorecap/templates/account/password_reset_from_key.html
djcorecap/templates/account/password_reset_from_key_done.html
djcorecap/templates/account/password_set.html
djcorecap/templates/account/signup.html
djcorecap/templates/account/signup_closed.html
djcorecap/templates/account/verification_sent.html
djcorecap/templates/account/verified_email_required.html
djcorecap/templates/djcorecap/base.html
djcorecap/templates/djcorecap/paginator.html
djcorecap/templates/djcorecap/test.html
djcorecap/templatetags/__init__.py
djcorecap/templatetags/djcorecap.py
djcorecap-1.0.1.dist-info/DESCRIPTION.rst
djcorecap-1.0.1.dist-info/METADATA
djcorecap-1.0.1.dist-info/RECORD
djcorecap-1.0.1.dist-info/WHEEL
djcorecap-1.0.1.dist-info/metadata.json
djcorecap-1.0.1.dist-info/top_level.txt
tests/__init__.py
tests/test.py
